poetry_test_pda_fga/__init__.py
poetry_test_pda_fga/data_treatment/__init__.py
poetry_test_pda_fga/data_treatment/data_pre_processing/__init__.py
poetry_test_pda_fga/data_treatment/data_pre_processing/concatenate_columns.py
poetry_test_pda_fga/index.py
poetry_test_pda_fga/parser/__init__.py
poetry_test_pda_fga/parser/feature_engineering/__init__.py
poetry_test_pda_fga/parser/feature_engineering/parser.py
poetry_test_pda_fga/parser/generator.py
poetry_test_pda_fga/parser/initial/__init__.py
poetry_test_pda_fga/parser/initial/parser.py
poetry_test_pda_fga/parser/initial/tests/__init__.py
poetry_test_pda_fga/parser/initial/tests/mock/ymal_mock.yaml
poetry_test_pda_fga/parser/initial/tests/mock/ymal_mock_fail.yaml
poetry_test_pda_fga/parser/initial/tests/parser_test.py
poetry_test_pda_fga/parser/tests/__init__.py
poetry_test_pda_fga/parser/tests/generator_test.py
poetry_test_pda_fga/parser/tests/mock/data_mock.csv
poetry_test_pda_fga/parser/tests/mock/first_case/ymal_mock.yaml
poetry_test_pda_fga/parser/tests/mock/second_case/ymal_mock.yaml
poetry_test_pda_fga/parser/tests/mock/third_case/ymal_mock.yaml
poetry_test_pda_fga/test_file_lib.py
poetry_test_pda_fga/yamls/basic_example.yaml
poetry_test_pda_fga-0.1.6.dist-info/entry_points.txt
poetry_test_pda_fga-0.1.6.dist-info/WHEEL
poetry_test_pda_fga-0.1.6.dist-info/METADATA
poetry_test_pda_fga-0.1.6.dist-info/RECORD
